README.rst
setup.py
spinpy/__init__.py
spinpy.egg-info/PKG-INFO
spinpy.egg-info/SOURCES.txt
spinpy.egg-info/dependency_links.txt
spinpy.egg-info/top_level.txt